assm/__init__.py
assm/__main__.py
assm/devices.py
assm-0.1.2.dist-info/LICENSE
assm-0.1.2.dist-info/WHEEL
assm-0.1.2.dist-info/METADATA
assm-0.1.2.dist-info/RECORD
